core/__init__.py
core/admin.py
core/apps.py
core/forms.py
core/models.py
core/signals.py
core/tests.py
core/urls.py
core/views.py
core/migrations/0001_initial.py
core/migrations/__init__.py
core/templates/__init__.py
usermangment/__init__.py
usermangment/asgi.py
usermangment/settings.py
usermangment/urls.py
usermangment/views.py
usermangment/wsgi.py
usermangment-1.1.dist-info/LICENSE
usermangment-1.1.dist-info/METADATA
usermangment-1.1.dist-info/WHEEL
usermangment-1.1.dist-info/entry_points.txt
usermangment-1.1.dist-info/top_level.txt
usermangment-1.1.dist-info/RECORD
