Metadata-Version: 2.1
Name: usermangment
Version: 1.1
Summary: A Django project for user management.
Home-page: https://github.com/hamed-jamali-software/usermangment
Author: Hamed Jamali
Author-email: hamed.jamali.software@gmail.com
Classifier: Programming Language :: Python :: 3
Classifier: Framework :: Django
Classifier: Operating System :: OS Independent
Requires-Python: >=3.6
License-File: LICENSE
Requires-Dist: Django >=5.0
Requires-Dist: django-bootstrap5
Requires-Dist: pillow
Requires-Dist: django-cleanup
Requires-Dist: django-allauth
Requires-Dist: django-htmx
Requires-Dist: pyjwt
Requires-Dist: cryptography
